tfw/__init__.py
tfw/models.py
tfw/types.py
tfw/core/__init__.py
tfw/core/converters.py
tfw/core/exceptions.py
tfw/core/utils.py
tfw/internal/__init__.py
tfw/internal/utils.py
tfw/internal/wrappers.py
tfw-0.1.1.dist-info/METADATA
tfw-0.1.1.dist-info/WHEEL
tfw-0.1.1.dist-info/top_level.txt
tfw-0.1.1.dist-info/RECORD
